{
  "routes": [
    {
      "method": "GET",
      "path": "/creators",
      "handler": "creator.find",
      "config": {
        "policies": []
      }
    },
    {
      "method": "GET",
      "path": "/creators/count",
      "handler": "creator.count",
      "config": {
        "policies": []
      }
    },
    {
      "method": "GET",
      "path": "/creators/:id",
      "handler": "creator.findOne",
      "config": {
        "policies": []
      }
    },
    {
      "method": "POST",
      "path": "/creators",
      "handler": "creator.create",
      "config": {
        "policies": []
      }
    },
    {
      "method": "PUT",
      "path": "/creators/:id",
      "handler": "creator.update",
      "config": {
        "policies": []
      }
    },
    {
      "method": "DELETE",
      "path": "/creators/:id",
      "handler": "creator.delete",
      "config": {
        "policies": []
      }
    }
  ]
}
